github_hooker/__init__.py
github_hooker/bottle.py
github_hooker/webhook_handler.py
github_hooker-0.2.dist-info/METADATA
github_hooker-0.2.dist-info/RECORD
github_hooker-0.2.dist-info/WHEEL
github_hooker-0.2.dist-info/entry_points.txt
github_hooker-0.2.dist-info/top_level.txt
