Metadata-Version: 2.1
Name: github-hooker
Version: 0.2
Summary: Simple github webhooks handler
Home-page: https://github.com/threatify/github-hooker
Author: Kashif Iftikhar
Author-email: kashif@compulife.com.pk
License: UNKNOWN
Keywords: github webhooks python handler
Platform: UNKNOWN
Classifier: Development Status :: 4 - Beta
Classifier: Intended Audience :: Developers
Classifier: Topic :: Software Development :: Build Tools
Classifier: Programming Language :: Python :: 3.5
Classifier: Programming Language :: Python :: 3.6
